README.rst
setup.py
Medea.egg-info/PKG-INFO
Medea.egg-info/SOURCES.txt
Medea.egg-info/dependency_links.txt
Medea.egg-info/not-zip-safe
Medea.egg-info/requires.txt
Medea.egg-info/top_level.txt
medea/__init__.py
medea/encoder.py
medea/mapper.py