Metadata-Version: 1.1
Name: Medea
Version: 0.3.2
Summary: JSON Object Mapper / Encoder
Home-page: http://github.com/kevinbeaty/medea
Author: Kevin Beaty
Author-email: kevin@simplectic.com
License: MIT
Platform: any
Classifier: Development Status :: 3 - Alpha
Classifier: Environment :: Web Environment
Classifier: Intended Audience :: Developers
Classifier: License :: OSI Approved :: MIT License
Classifier: Topic :: Internet :: WWW/HTTP
Classifier: Topic :: Software Development :: Libraries :: Python Modules
Classifier: Topic :: Text Processing :: Markup
